<?xml version="1.0" encoding="UTF-8" standalone="yes" ?>
<map>
<group name="Vanilla_Land_misc_chickenCoop" pos="199.758 385.183 12520" rpy="-0 0 50.8974" a="39.1026" />
<group name="Vanilla_Land_misc_chickenCoop" pos="359.627 134.246 5208.34" rpy="-0 0 21.1959" a="68.8041" />
<group name="Vanilla_Land_misc_chickenCoop" pos="327.085 287.934 8585.56" rpy="-0 0 44.6984" a="45.3016" />
<group name="Vanilla_Land_misc_chickenCoop" pos="404.718 134.215 5162.32" rpy="-0 0 -156.372" a="-113.628" />
<group name="Vanilla_Land_misc_chickenCoop" pos="451.795 132.556 5164.89" rpy="-0 0 -82.5215" a="172.522" />
<group name="Vanilla_Land_misc_chickenCoop" pos="580.915 142.769 5314.08" rpy="-0 0 0.712718" a="89.2873" />
<group name="Vanilla_Land_misc_chickenCoop" pos="714.048 141.153 5644.89" rpy="-0 0 145.693" a="-55.6935" />
<group name="Vanilla_Land_misc_chickenCoop" pos="740.157 131.525 4618.61" rpy="-0 0 -58.3921" a="148.392" />
<group name="Vanilla_Land_misc_chickenCoop" pos="1234.3 279.719 8733.03" rpy="-0 0 6.56083" a="83.4392" />
<group name="Vanilla_Land_misc_chickenCoop" pos="1227.58 279.083 8820.76" rpy="-0 0 126.465" a="-36.4652" />
<group name="Vanilla_Land_misc_chickenCoop" pos="1250.42 278.851 8912.93" rpy="-0 0 -77.8289" a="167.829" />
<group name="Vanilla_Land_misc_chickenCoop" pos="1222.51 298.882 12043.8" rpy="0.0195592 -0.00296065 8.60745" a="81.3925" />
<group name="Vanilla_Land_misc_chickenCoop" pos="1517.67 301.771 8924.06" rpy="-0 0 -103.268" a="-166.732" />
<group name="Vanilla_Land_misc_chickenCoop" pos="1554.59 302.615 8921.61" rpy="-0 0 160.319" a="-70.3186" />
<group name="Vanilla_Land_misc_chickenCoop" pos="1527.38 277.732 12051.7" rpy="-0 0 5.12564" a="84.8744" />
<group name="Vanilla_Land_misc_chickenCoop" pos="1577.26 302.12 8965.53" rpy="-0 0 -179.358" a="-90.6417" />
<group name="Vanilla_Land_misc_chickenCoop" pos="1577.94 302.239 8994.77" rpy="-0 0 169.592" a="-79.5924" />
<group name="Vanilla_Land_misc_chickenCoop" pos="1611.16 302.768 8978.94" rpy="-0 0 104.27" a="-14.2703" />
<group name="Vanilla_Land_misc_chickenCoop" pos="1608.43 274.615 11999.6" rpy="0.0363601 -0.0425286 49.471" a="40.529" />
<group name="Vanilla_Land_misc_chickenCoop" pos="1585.43 274.932 12019.2" rpy="-0 0 57.1719" a="32.8281" />
<group name="Vanilla_Land_misc_chickenCoop" pos="1648.2 144.724 3774.94" rpy="-0 0 75" a="15" />
<group name="Vanilla_Land_misc_chickenCoop" pos="1654.85 142.118 3729.07" rpy="-0 0 73.5804" a="16.4196" />
<group name="Vanilla_Land_misc_chickenCoop" pos="1655.97 144.396 3857.63" rpy="-0 0 166" a="-76" />
<group name="Vanilla_Land_misc_chickenCoop" pos="1639.7 271.479 12016.6" rpy="0.0546904 0.0362459 -33.5343" a="123.534" />
<group name="Vanilla_Land_misc_chickenCoop" pos="1658.63 269.239 12060.6" rpy="-0 0 85.9278" a="4.0722" />
<group name="Vanilla_Land_misc_chickenCoop" pos="1721.62 142.261 3692.15" rpy="-0 0 4.50785" a="85.4922" />
<group name="Vanilla_Land_misc_chickenCoop" pos="1688.01 144.806 3922.93" rpy="-0 0 -24" a="114" />
<group name="Vanilla_Land_misc_chickenCoop" pos="1752.09 6.70464 2210.97" rpy="-0 0 -95" a="-175" />
<group name="Vanilla_Land_misc_chickenCoop" pos="1881.73 142.548 3905.62" rpy="-0 0 25.2229" a="64.7771" />
<group name="Vanilla_Land_misc_chickenCoop" pos="1936.48 6.75523 2190.32" rpy="-0 0 75" a="15" />
<group name="Vanilla_Land_misc_chickenCoop" pos="1975.77 237.3 7197.07" rpy="-0 0 -170.179" a="-99.821" />
<group name="Vanilla_Land_misc_chickenCoop" pos="1944.51 257.022 7350.57" rpy="-0 0 43.4969" a="46.5031" />
<group name="Vanilla_Land_misc_chickenCoop" pos="1953.2 257.838 7370.52" rpy="-0 0 167.956" a="-77.9564" />
<group name="Vanilla_Land_misc_chickenCoop" pos="2013.31 242.498 7046.99" rpy="-0 0 93.0991" a="-3.0991" />
<group name="Vanilla_Land_misc_chickenCoop" pos="2006.18 237.58 7151.47" rpy="-0 0 97.2447" a="-7.2447" />
<group name="Vanilla_Land_misc_chickenCoop" pos="1989.41 242.649 7245.25" rpy="-0 0 -159.546" a="-110.454" />
<group name="Vanilla_Land_misc_chickenCoop" pos="2022.06 254.531 7343.47" rpy="-0 0 -56.2074" a="146.207" />
<group name="Vanilla_Land_misc_chickenCoop" pos="2047.73 259.664 7292.57" rpy="-0 0 178.788" a="-88.7882" />
<group name="Vanilla_Land_misc_chickenCoop" pos="2120.92 447.313 15074.6" rpy="0.026948 -0.0289688 47.0697" a="42.9303" />
<group name="Vanilla_Land_misc_chickenCoop" pos="2115 446.824 15073.9" rpy="-0 0 0" a="90" />
<group name="Vanilla_Land_misc_chickenCoop" pos="2210.72 265.111 10994" rpy="-0.00202151 0.0196784 -95.8652" a="-174.135" />
<group name="Vanilla_Land_misc_chickenCoop" pos="2217.34 265.76 11152.3" rpy="0.0124211 0.0319333 -68.7455" a="158.745" />
<group name="Vanilla_Land_misc_chickenCoop" pos="2249.82 268.297 11004" rpy="-0 0 -74.2744" a="164.274" />
<group name="Vanilla_Land_misc_chickenCoop" pos="2251.87 268.273 11007.1" rpy="-0 0 -57.9183" a="147.918" />
<group name="Vanilla_Land_misc_chickenCoop" pos="2266.91 436.19 15218.1" rpy="-0.0092528 -0.0174847 117.888" a="-27.8876" />
<group name="Vanilla_Land_misc_chickenCoop" pos="2265.35 434.56 15226.2" rpy="-0 0 77.6734" a="12.3266" />
<group name="Vanilla_Land_misc_chickenCoop" pos="2267.19 434.059 15231.2" rpy="-0 0 113.287" a="-23.2865" />
<group name="Vanilla_Land_misc_chickenCoop" pos="2428.14 286.649 10966.1" rpy="-0 0 -94.8186" a="-175.181" />
<group name="Vanilla_Land_misc_chickenCoop" pos="2447.82 288.097 11004.7" rpy="-0.000370134 0.0279735 -90.7581" a="-179.242" />
<group name="Vanilla_Land_misc_chickenCoop" pos="2448.09 288.122 11000.7" rpy="-0 0 -111.815" a="-158.185" />
<group name="Vanilla_Land_misc_chickenCoop" pos="2497.77 254.791 9667.19" rpy="-0 0 90" a="0" />
<group name="Vanilla_Land_misc_chickenCoop" pos="2605.52 194.323 4966.86" rpy="-0 0 167.272" a="-77.2721" />
<group name="Vanilla_Land_misc_chickenCoop" pos="2602.6 194.356 4966.39" rpy="-0 0 172.671" a="-82.6715" />
<group name="Vanilla_Land_misc_chickenCoop" pos="2623.34 195.947 5046.01" rpy="-0.0142877 0.0136817 -136.241" a="-133.759" />
<group name="Vanilla_Land_misc_chickenCoop" pos="2621.81 196.003 5048.47" rpy="-0 0 -109.223" a="-160.777" />
<group name="Vanilla_Land_misc_chickenCoop" pos="2634.5 199.435 5207.63" rpy="0.0136525 0.0420755 -72.023" a="162.023" />
<group name="Vanilla_Land_misc_chickenCoop" pos="2637.94 259.599 9586.28" rpy="-0 0 -74.7392" a="164.739" />
<group name="Vanilla_Land_misc_chickenCoop" pos="2639.29 223.602 12307.5" rpy="-0.0523322 0.000841586 -179.079" a="-90.9213" />
<group name="Vanilla_Land_misc_chickenCoop" pos="2601.46 224.518 12372.1" rpy="0.0188513 0.00599639 -17.6453" a="107.645" />
<group name="Vanilla_Land_misc_chickenCoop" pos="2666.65 221.77 12315.3" rpy="-0 0 99.174" a="-9.17405" />
<group name="Vanilla_Land_misc_chickenCoop" pos="2696.13 220.446 12327.7" rpy="-0.00344853 -0.0277626 97.0807" a="-7.0807" />
<group name="Vanilla_Land_misc_chickenCoop" pos="2674.02 221.504 12363.3" rpy="-0 0 91.5236" a="-1.52361" />
<group name="Vanilla_Land_misc_chickenCoop" pos="2744.07 274.736 9917.84" rpy="-0 0 30" a="60" />
<group name="Vanilla_Land_misc_chickenCoop" pos="2752.83 274.678 10027.4" rpy="-0 0 -95" a="-175" />
<group name="Vanilla_Land_misc_chickenCoop" pos="2725.95 274.758 10023.1" rpy="-0 0 90" a="0" />
<group name="Vanilla_Land_misc_chickenCoop" pos="2711.29 219.285 12332.4" rpy="-0 0 -128.003" a="-141.997" />
<group name="Vanilla_Land_misc_chickenCoop" pos="2712.16 220.482 12376.8" rpy="-0 0 -86.4377" a="176.438" />
<group name="Vanilla_Land_misc_chickenCoop" pos="2817.86 274.734 9878.04" rpy="-0 0 50" a="40" />
<group name="Vanilla_Land_misc_chickenCoop" pos="2790.45 222.752 12268.4" rpy="0.00858064 -0.0331722 75.4972" a="14.5028" />
<group name="Vanilla_Land_misc_chickenCoop" pos="2846.82 212.384 5430.37" rpy="-0 0 -134.282" a="-135.718" />
<group name="Vanilla_Land_misc_chickenCoop" pos="2845.26 212.363 5432.24" rpy="-0 0 -127.487" a="-142.513" />
<group name="Vanilla_Land_misc_chickenCoop" pos="2933.41 323.683 7737.48" rpy="-0 0 -139.603" a="-130.397" />
<group name="Vanilla_Land_misc_chickenCoop" pos="2932.02 323.584 7740" rpy="-0 0 -79.0887" a="169.089" />
<group name="Vanilla_Land_misc_chickenCoop" pos="2917.48 215.114 12415" rpy="0.0157016 0.0120328 -37.4645" a="127.465" />
<group name="Vanilla_Land_misc_chickenCoop" pos="2932.68 390.033 15199.8" rpy="0.00483637 -0.0191817 75.8487" a="14.1513" />
<group name="Vanilla_Land_misc_chickenCoop" pos="2989.59 312.867 7875.89" rpy="-0 0 135.653" a="-45.6531" />
<group name="Vanilla_Land_misc_chickenCoop" pos="2991.9 312.619 7878.33" rpy="-0.0274064 -0.0399621 124.443" a="-34.4427" />
<group name="Vanilla_Land_misc_chickenCoop" pos="2952.06 211.808 12535.3" rpy="-0 0 119.399" a="-29.3994" />
<group name="Vanilla_Land_misc_chickenCoop" pos="2941.03 389.591 15202.4" rpy="-0 0 -16.6879" a="106.688" />
<group name="Vanilla_Land_misc_chickenCoop" pos="3013.87 323.11 7729.06" rpy="-0 0 37.6089" a="52.3911" />
<group name="Vanilla_Land_misc_chickenCoop" pos="3003 312.162 7894.77" rpy="-0 0 -136.671" a="-133.329" />
<group name="Vanilla_Land_misc_chickenCoop" pos="3019.28 209.872 12553.1" rpy="-0 0 31.7008" a="58.2992" />
<group name="Vanilla_Land_misc_chickenCoop" pos="3105.19 281.824 9207.44" rpy="-0 0 -55" a="145" />
<group name="Vanilla_Land_misc_chickenCoop" pos="3121.02 226.242 3935.72" rpy="-0 0 -15.8658" a="105.866" />
<group name="Vanilla_Land_misc_chickenCoop" pos="3184.81 205.885 4004.3" rpy="-0 0 35.3605" a="54.6395" />
<group name="Vanilla_Land_misc_chickenCoop" pos="3200.5 302.585 8036.16" rpy="-0.0180617 -0.0529577 108.832" a="-18.8324" />
<group name="Vanilla_Land_misc_chickenCoop" pos="3198.93 302.688 8033.2" rpy="-0 0 120.074" a="-30.0738" />
<group name="Vanilla_Land_misc_chickenCoop" pos="3235.68 297.3 8122.66" rpy="-0.0181846 0.00778768 -156.817" a="-113.183" />
<group name="Vanilla_Land_misc_chickenCoop" pos="3238.67 297.079 8121.15" rpy="-0 0 178.024" a="-88.024" />
<group name="Vanilla_Land_misc_chickenCoop" pos="3198.18 361.969 15280.1" rpy="-0 0 -123.021" a="-146.979" />
<group name="Vanilla_Land_misc_chickenCoop" pos="3196.32 361.982 15282.8" rpy="-0 0 -97.0511" a="-172.949" />
<group name="Vanilla_Land_misc_chickenCoop" pos="3202.19 361.93 15281.8" rpy="-0.0178884 -0.00844577 154.726" a="-64.7263" />
<group name="Vanilla_Land_misc_chickenCoop" pos="3266.22 193.027 3863.13" rpy="-0 0 9.85472" a="80.1453" />
<group name="Vanilla_Land_misc_chickenCoop" pos="3264.73 192.608 3947.98" rpy="0.0182831 -0.00755348 22.4475" a="67.5525" />
<group name="Vanilla_Land_misc_chickenCoop" pos="3241.12 202.537 4025.25" rpy="0.0150116 -0.0308005 64.0162" a="25.9838" />
<group name="Vanilla_Land_misc_chickenCoop" pos="3261.23 201.651 12896.3" rpy="-0 0 -127.472" a="-142.528" />
<group name="Vanilla_Land_misc_chickenCoop" pos="3294.35 200.737 12973.2" rpy="-0 0 -127.686" a="-142.314" />
<group name="Vanilla_Land_misc_chickenCoop" pos="3267.89 201.835 13124.6" rpy="0.0498455 0.0322102 -32.8706" a="122.871" />
<group name="Vanilla_Land_misc_chickenCoop" pos="3249.52 202.854 13147.7" rpy="-0.0624314 -0.0397635 147.506" a="-57.5064" />
<group name="Vanilla_Land_misc_chickenCoop" pos="3274.13 202.51 13166.5" rpy="-0.0163567 -0.0111259 145.776" a="-55.7763" />
<group name="Vanilla_Land_misc_chickenCoop" pos="3350.66 184.442 3884.91" rpy="-0.00105089 -0.019754 93.0452" a="-3.04519" />
<group name="Vanilla_Land_misc_chickenCoop" pos="3315.92 187.09 3969.44" rpy="-0.021882 0.0174309 -141.46" a="-128.54" />
<group name="Vanilla_Land_misc_chickenCoop" pos="3304.89 202.003 13181.1" rpy="-0.0405358 -0.0177082 156.402" a="-66.4017" />
<group name="Vanilla_Land_misc_chickenCoop" pos="3393.92 242.552 4936.29" rpy="-0 0 45.2676" a="44.7324" />
<group name="Vanilla_Land_misc_chickenCoop" pos="3412.34 206.647 12645.4" rpy="-0.00256264 -0.0196153 97.4432" a="-7.44323" />
<group name="Vanilla_Land_misc_chickenCoop" pos="3448.29 205.696 12664.5" rpy="0.032269 0.011521 -19.6482" a="109.648" />
<group name="Vanilla_Land_misc_chickenCoop" pos="3434.61 199.796 13231.1" rpy="0.0263072 0.00951777 -19.8898" a="109.89" />
<group name="Vanilla_Land_misc_chickenCoop" pos="3460.39 231.062 13903.8" rpy="-0 0 169.343" a="-79.3426" />
<group name="Vanilla_Land_misc_chickenCoop" pos="3465.28 231.039 13909.2" rpy="-0 0 41.1209" a="48.8791" />
<group name="Vanilla_Land_misc_chickenCoop" pos="3493.55 6.27124 2414.2" rpy="-0 0 -110" a="-160" />
<group name="Vanilla_Land_misc_chickenCoop" pos="3547.13 244.063 14236.7" rpy="-0 0 -177.255" a="-92.7448" />
<group name="Vanilla_Land_misc_chickenCoop" pos="3543.64 244.243 14238.2" rpy="-0 0 -104.646" a="-165.354" />
<group name="Vanilla_Land_misc_chickenCoop" pos="3698.29 6.99499 2462.61" rpy="-0 0 165" a="-75" />
<group name="Vanilla_Land_misc_chickenCoop" pos="3675.61 304.539 8241.41" rpy="-0 0 119.086" a="-29.0856" />
<group name="Vanilla_Land_misc_chickenCoop" pos="3723.51 199.307 13194.3" rpy="-0 0 -94.8288" a="-175.171" />
<group name="Vanilla_Land_misc_chickenCoop" pos="3771.81 198.479 13185.6" rpy="-0 0 169.187" a="-79.187" />
<group name="Vanilla_Land_misc_chickenCoop" pos="3806.13 307.834 8728.55" rpy="-0 0 110.258" a="-20.2581" />
<group name="Vanilla_Land_misc_chickenCoop" pos="3801.1 307.87 8723.56" rpy="-0 0 -147.499" a="-122.501" />
<group name="Vanilla_Land_misc_chickenCoop" pos="3830.92 312.272 9013.74" rpy="-0 0 -137.994" a="-132.006" />
<group name="Vanilla_Land_misc_chickenCoop" pos="3834.32 312.09 9009.12" rpy="-0 0 -152.722" a="-117.278" />
<group name="Vanilla_Land_misc_chickenCoop" pos="3821.11 314.237 9072.88" rpy="0.0453324 -0.0171188 20.6879" a="69.3121" />
<group name="Vanilla_Land_misc_chickenCoop" pos="3896.53 173.066 3569.29" rpy="-0.000243891 0.0395496 179.647" a="-89.6467" />
<group name="Vanilla_Land_misc_chickenCoop" pos="3895.4 311.794 8914.46" rpy="0.000181059 -0.0197812 89.4756" a="0.524422" />
<group name="Vanilla_Land_misc_chickenCoop" pos="3860.95 312.66 9032.08" rpy="-0 0 5.53587" a="84.4641" />
<group name="Vanilla_Land_misc_chickenCoop" pos="3875.88 195.547 12819.1" rpy="-0 0 138.035" a="-48.035" />
<group name="Vanilla_Land_misc_chickenCoop" pos="3908.16 312.474 8911.63" rpy="-0 0 -180" a="-90" />
<group name="Vanilla_Land_misc_chickenCoop" pos="3993.71 314.411 8809.19" rpy="-0 0 95.0917" a="-5.09168" />
<group name="Vanilla_Land_misc_chickenCoop" pos="3991.21 314.01 8807.08" rpy="-0 0 172.747" a="-82.7474" />
<group name="Vanilla_Land_misc_chickenCoop" pos="3967.12 212.582 13933.5" rpy="-0 0 -80.5415" a="170.542" />
<group name="Vanilla_Land_misc_chickenCoop" pos="4424.15 4.92164 2362.48" rpy="-0.0170714 0.0221636 -127.605" a="-142.395" />
<group name="Vanilla_Land_misc_chickenCoop" pos="4392.66 178.1 3930.09" rpy="-0 0 90" a="-1.52588e-05" />
<group name="Vanilla_Land_misc_chickenCoop" pos="4408.12 236.754 4702.32" rpy="0.00447867 0.0192683 -76.9147" a="166.915" />
<group name="Vanilla_Land_misc_chickenCoop" pos="4421.75 300.188 6452.1" rpy="-0 0 -119.302" a="-150.698" />
<group name="Vanilla_Land_misc_chickenCoop" pos="4463.88 232.892 4607.12" rpy="-0 0 145.392" a="-55.3925" />
<group name="Vanilla_Land_misc_chickenCoop" pos="4474.95 296.458 6381.64" rpy="-0 0 -180" a="-90" />
<group name="Vanilla_Land_misc_chickenCoop" pos="4483.51 184.283 13319.3" rpy="-0.0187932 0.0207237 -132.203" a="-137.797" />
<group name="Vanilla_Land_misc_chickenCoop" pos="4455.79 476.269 15207" rpy="-0 0 91.9059" a="-1.90594" />
<group name="Vanilla_Land_misc_chickenCoop" pos="4557.95 3.27588 2366.23" rpy="-0.0395523 -0.00100125 178.55" a="-88.5499" />
<group name="Vanilla_Land_misc_chickenCoop" pos="4529.2 10.7396 2633.18" rpy="-0 0 39.4085" a="50.5915" />
<group name="Vanilla_Land_misc_chickenCoop" pos="4504.05 474.472 15244.8" rpy="-0 0 -99.7468" a="-170.253" />
<group name="Vanilla_Land_misc_chickenCoop" pos="4516.14 474.472 15273.9" rpy="-0 0 -104.648" a="-165.352" />
<group name="Vanilla_Land_misc_chickenCoop" pos="4563.26 3.53597 2366.27" rpy="-0.0292537 -0.0266385 137.679" a="-47.6789" />
<group name="Vanilla_Land_misc_chickenCoop" pos="4644.25 476.205 15104.9" rpy="-0 0 105.444" a="-15.4445" />
<group name="Vanilla_Land_misc_chickenCoop" pos="4730.26 272.54 6845.88" rpy="-0 0 -90" a="-180" />
<group name="Vanilla_Land_misc_chickenCoop" pos="4769.78 475.495 15013.9" rpy="-0.0146827 -0.0309587 115.374" a="-25.3735" />
<group name="Vanilla_Land_misc_chickenCoop" pos="4787.68 474.755 15062.6" rpy="-0.0147108 -0.0367285 111.827" a="-21.8274" />
<group name="Vanilla_Land_misc_chickenCoop" pos="4857.88 321.879 5640.54" rpy="-0 0 -48.9532" a="138.953" />
<group name="Vanilla_Land_misc_chickenCoop" pos="4809.13 269.859 6767.54" rpy="-0 0 -150" a="-120" />
<group name="Vanilla_Land_misc_chickenCoop" pos="4870.34 318.381 5737.73" rpy="-0 0 60.232" a="29.768" />
<group name="Vanilla_Land_misc_chickenCoop" pos="4901.22 319.91 5712.87" rpy="-0 0 -28.9884" a="118.988" />
<group name="Vanilla_Land_misc_chickenCoop" pos="4869.31 318.315 5741.35" rpy="-0 0 77.5563" a="12.4437" />
<group name="Vanilla_Land_misc_chickenCoop" pos="4907.74 250.859 11825.9" rpy="-0.0435963 -0.0598179 126.085" a="-36.0852" />
<group name="Vanilla_Land_misc_chickenCoop" pos="4907.96 250.435 11830.8" rpy="0.0612759 -0.0306814 26.5975" a="63.4025" />
<group name="Vanilla_Land_misc_chickenCoop" pos="4878.1 475.172 14971.1" rpy="-0.0334831 0.00727339 -167.744" a="-102.256" />
<group name="Vanilla_Land_misc_chickenCoop" pos="4908.64 477.329 15024.4" rpy="0.0106134 0.0429429 -76.1175" a="166.117" />
<group name="Vanilla_Land_misc_chickenCoop" pos="4956.21 170.135 12771.1" rpy="-0 0 -81.2272" a="171.227" />
<group name="Vanilla_Land_misc_chickenCoop" pos="4926.13 167.876 12833.1" rpy="-0 0 101.35" a="-11.35" />
<group name="Vanilla_Land_misc_chickenCoop" pos="4947.86 474.619 15084.5" rpy="-0 0 175.444" a="-85.4438" />
<group name="Vanilla_Land_misc_chickenCoop" pos="4978.33 474.576 15072.9" rpy="-0.0197483 -0.00115457 176.654" a="-86.654" />
<group name="Vanilla_Land_misc_chickenCoop" pos="4946.04 474.605 15179" rpy="-0 0 -74.9881" a="164.988" />
<group name="Vanilla_Land_misc_chickenCoop" pos="4965.38 474.439 15170.4" rpy="-0.000215812 0.0279752 -90.442" a="-179.558" />
<group name="Vanilla_Land_misc_chickenCoop" pos="5012.06 195.336 13486.6" rpy="0.00411862 -0.0482816 85.1242" a="4.87577" />
<group name="Vanilla_Land_misc_chickenCoop" pos="5167.56 478.227 14940.3" rpy="0.0261925 -0.00982888 20.5688" a="69.4312" />
<group name="Vanilla_Land_misc_chickenCoop" pos="5175.18 480.72 15036.8" rpy="-0 0 160.836" a="-70.836" />
<group name="Vanilla_Land_misc_chickenCoop" pos="5232.47 482.283 15048" rpy="-0 0 162.732" a="-72.732" />
<group name="Vanilla_Land_misc_chickenCoop" pos="5221.02 481.046 15075.9" rpy="-0 0 162.732" a="-72.732" />
<group name="Vanilla_Land_misc_chickenCoop" pos="5307.69 334.619 8577.23" rpy="-0.0110638 -0.0163845 34.0296" a="55.9704" />
<group name="Vanilla_Land_misc_chickenCoop" pos="5370.75 335.635 8508.98" rpy="-0 0 134" a="-44" />
<group name="Vanilla_Land_misc_chickenCoop" pos="5430.26 161.224 12561.5" rpy="-0 0 90.5955" a="-0.595505" />
<group name="Vanilla_Land_misc_chickenCoop" pos="5400.14 160.728 12572" rpy="-0 0 -43.4412" a="133.441" />
<group name="Vanilla_Land_misc_chickenCoop" pos="5402 166.288 12732" rpy="0.00512222 0.0439374 -83.3505" a="173.35" />
<group name="Vanilla_Land_misc_chickenCoop" pos="5467.38 330.11 8521.61" rpy="-0.0374762 -0.023425 57.992" a="32.008" />
<group name="Vanilla_Land_misc_chickenCoop" pos="5603.22 191.64 13139.9" rpy="-0 0 -151.132" a="-118.868" />
<group name="Vanilla_Land_misc_chickenCoop" pos="5687.57 225.22 13574.9" rpy="-0 0 166.545" a="-76.5454" />
<group name="Vanilla_Land_misc_chickenCoop" pos="5666.78 227.062 13594.5" rpy="-0.000741619 -0.034256 91.2402" a="-1.24022" />
<group name="Vanilla_Land_misc_chickenCoop" pos="5684.97 481.757 14874.6" rpy="-0 0 171.063" a="-81.0631" />
<group name="Vanilla_Land_misc_chickenCoop" pos="5688.17 481.754 14900.1" rpy="-0 0 80.1133" a="9.88671" />
<group name="Vanilla_Land_misc_chickenCoop" pos="5712.66 481.58 14903.4" rpy="-0 0 80.7548" a="9.24525" />
<group name="Vanilla_Land_misc_chickenCoop" pos="5774.09 82.0873 2769.62" rpy="-0 0 90" a="0" />
<group name="Vanilla_Land_misc_chickenCoop" pos="5774.12 82.0815 2772.07" rpy="-0 0 90" a="0" />
<group name="Vanilla_Land_misc_chickenCoop" pos="5766.27 81.1551 4078.09" rpy="-0 0 -112.143" a="-157.857" />
<group name="Vanilla_Land_misc_chickenCoop" pos="5846.02 74.2576 4003.18" rpy="-0 0 0" a="90" />
<group name="Vanilla_Land_misc_chickenCoop" pos="5847.2 132.659 4853.62" rpy="-0 0 -41.8977" a="131.898" />
<group name="Vanilla_Land_misc_chickenCoop" pos="5855.17 284.386 9967.38" rpy="-0 0 -180" a="-90" />
<group name="Vanilla_Land_misc_chickenCoop" pos="5854.75 272.338 10225.8" rpy="-0 0 -69" a="159" />
<group name="Vanilla_Land_misc_chickenCoop" pos="5855.54 272.25 10227.8" rpy="-0 0 -69" a="159" />
<group name="Vanilla_Land_misc_chickenCoop" pos="5881.86 141.904 4746.25" rpy="-0 0 -23.1837" a="113.184" />
<group name="Vanilla_Land_misc_chickenCoop" pos="5931.6 268.56 10336" rpy="-0 0 124" a="-34" />
<group name="Vanilla_Land_misc_chickenCoop" pos="5926.57 226.401 13475.9" rpy="-0 0 -137.913" a="-132.087" />
<group name="Vanilla_Land_misc_chickenCoop" pos="5913.49 229.031 13547.6" rpy="-0 0 -132.4" a="-137.6" />
<group name="Vanilla_Land_misc_chickenCoop" pos="5899.4 231.24 13582.3" rpy="-0.0345653 0.0192518 -150.884" a="-119.116" />
<group name="Vanilla_Land_misc_chickenCoop" pos="5902.62 231.306 13580.4" rpy="-0 0 -167.24" a="-102.76" />
<group name="Vanilla_Land_misc_chickenCoop" pos="5913.18 233.156 13606.9" rpy="-0 0 -145.167" a="-124.833" />
<group name="Vanilla_Land_misc_chickenCoop" pos="5917.75 233.244 13605.8" rpy="-0.015696 -0.023158 124.129" a="-34.1286" />
<group name="Vanilla_Land_misc_chickenCoop" pos="5960.4 227.892 13512.1" rpy="0.063209 -0.0476028 36.9834" a="53.0166" />
<group name="Vanilla_Land_misc_chickenCoop" pos="5955.61 227.78 13512.7" rpy="0.0545933 0.0414206 -37.188" a="127.188" />
<group name="Vanilla_Land_misc_chickenCoop" pos="6044.5 159.545 4909.24" rpy="-0 0 -101.838" a="-168.162" />
<group name="Vanilla_Land_misc_chickenCoop" pos="6003.87 269.071 10306.4" rpy="-0 0 -70" a="160" />
<group name="Vanilla_Land_misc_chickenCoop" pos="6026.01 267.741 10366.5" rpy="-0 0 -57" a="147" />
<group name="Vanilla_Land_misc_chickenCoop" pos="6029.03 267.736 10478.3" rpy="-0 0 21" a="69" />
<group name="Vanilla_Land_misc_chickenCoop" pos="6112.81 5.13076 1922.77" rpy="-0 0 87.4857" a="2.51431" />
<group name="Vanilla_Land_misc_chickenCoop" pos="6062.9 32.7694 2939.45" rpy="-0 0 2.49763" a="87.5024" />
<group name="Vanilla_Land_misc_chickenCoop" pos="6085.86 42.9375 2995.15" rpy="-0 0 -89.719" a="179.719" />
<group name="Vanilla_Land_misc_chickenCoop" pos="6119.47 158.044 12690.6" rpy="-0 0 -168.479" a="-101.521" />
<group name="Vanilla_Land_misc_chickenCoop" pos="6140.03 26.5468 2915.95" rpy="-0 0 -2.08478" a="92.0848" />
<group name="Vanilla_Land_misc_chickenCoop" pos="6120.54 33.1144 2961.94" rpy="-0 0 -0.181291" a="90.1813" />
<group name="Vanilla_Land_misc_chickenCoop" pos="6148.62 253.737 10765.5" rpy="-0 0 -9.99999" a="100" />
<group name="Vanilla_Land_misc_chickenCoop" pos="6298.71 5.03278 2151.4" rpy="-0 0 134.411" a="-44.4109" />
<group name="Vanilla_Land_misc_chickenCoop" pos="6301.36 38.1354 3094.35" rpy="-0 0 -59.8183" a="149.818" />
<group name="Vanilla_Land_misc_chickenCoop" pos="6364.04 6.19107 2234.98" rpy="-0 0 129.074" a="-39.0738" />
<group name="Vanilla_Land_misc_chickenCoop" pos="6388.84 21.8038 3197.28" rpy="-0 0 -140" a="-130" />
<group name="Vanilla_Land_misc_chickenCoop" pos="6363.32 151.685 12679.3" rpy="-0.0196646 0.0280593 -125.024" a="-144.976" />
<group name="Vanilla_Land_misc_chickenCoop" pos="6404.81 151.733 12732.9" rpy="-0 0 55.7357" a="34.2643" />
<group name="Vanilla_Land_misc_chickenCoop" pos="6442.75 15.9658 3092.12" rpy="-0 0 87.7572" a="2.24281" />
<group name="Vanilla_Land_misc_chickenCoop" pos="6457.75 18.1971 3140.59" rpy="-0 0 125" a="-34.9999" />
<group name="Vanilla_Land_misc_chickenCoop" pos="6476.65 322.688 6143.96" rpy="-0 0 130" a="-40" />
<group name="Vanilla_Land_misc_chickenCoop" pos="6438.68 150.202 12698.6" rpy="0.0125945 -0.0249807 63.2441" a="26.7559" />
<group name="Vanilla_Land_misc_chickenCoop" pos="6439.27 149.926 12694.9" rpy="-0 0 79.6002" a="10.3998" />
<group name="Vanilla_Land_misc_chickenCoop" pos="6462.82 150.159 12723.9" rpy="-0 0 170.011" a="-80.0111" />
<group name="Vanilla_Land_misc_chickenCoop" pos="6528.89 369.284 14366.8" rpy="-0 0 176.461" a="-86.4608" />
<group name="Vanilla_Land_misc_chickenCoop" pos="6536.13 369.337 14396.9" rpy="0.0146026 -0.0133451 42.4237" a="47.5763" />
<group name="Vanilla_Land_misc_chickenCoop" pos="6555.16 322.754 6115.86" rpy="-0 0 70" a="20" />
<group name="Vanilla_Land_misc_chickenCoop" pos="6627.5 377.228 14475.9" rpy="-0 0 -60.0395" a="150.04" />
<group name="Vanilla_Land_misc_chickenCoop" pos="6629.52 377.233 14478" rpy="0.0229528 0.0159946 -34.8706" a="124.871" />
<group name="Vanilla_Land_misc_chickenCoop" pos="6676.01 377.175 14279.7" rpy="0.000893301 0.0484488 -88.9437" a="178.944" />
<group name="Vanilla_Land_misc_chickenCoop" pos="6676.76 377.244 14282.1" rpy="0.0254499 0.0302934 -49.9659" a="139.966" />
<group name="Vanilla_Land_misc_chickenCoop" pos="6761.05 376.385 14264.9" rpy="0.0169331 -0.0297874 60.3833" a="29.6167" />
<group name="Vanilla_Land_misc_chickenCoop" pos="6759.17 376.554 14267.1" rpy="0.0279976 -0.0197524 35.2031" a="54.7969" />
<group name="Vanilla_Land_misc_chickenCoop" pos="6753.41 377.092 14263.4" rpy="-0.00886369 0.0176851 -116.62" a="-153.38" />
<group name="Vanilla_Land_misc_chickenCoop" pos="6722.67 377.794 14402.2" rpy="0.0191595 0.0203856 -46.7759" a="136.776" />
<group name="Vanilla_Land_misc_chickenCoop" pos="6725.85 377.795 14405.6" rpy="-0 0 -9.7258" a="99.7258" />
<group name="Vanilla_Land_misc_chickenCoop" pos="6819.97 139.718 12563.1" rpy="-0 0 -167.611" a="-102.389" />
<group name="Vanilla_Land_misc_chickenCoop" pos="6785.19 141.167 12567.3" rpy="-0 0 46.2163" a="43.7837" />
<group name="Vanilla_Land_misc_chickenCoop" pos="7465.14 214.631 5117.83" rpy="-0 0 -5.00002" a="95" />
<group name="Vanilla_Land_misc_chickenCoop" pos="7442.25 123.201 12651.7" rpy="0.0227673 -0.037926 59.0232" a="30.9768" />
<group name="Vanilla_Land_misc_chickenCoop" pos="7442.77 123.038 12648" rpy="-0 0 93.4237" a="-3.42368" />
<group name="Vanilla_Land_misc_chickenCoop" pos="7541.68 214.69 5129.14" rpy="0.0076642 -0.0588611 -7.41864" a="97.4186" />
<group name="Vanilla_Land_misc_chickenCoop" pos="7522.5 221.41 5256.14" rpy="-0 0 -45" a="135" />
<group name="Vanilla_Land_misc_chickenCoop" pos="7538.24 217.311 13600.5" rpy="-0 0 107.251" a="-17.2512" />
<group name="Vanilla_Land_misc_chickenCoop" pos="7536.27 217.525 13603.8" rpy="0.00624785 -0.0187694 71.5887" a="18.4113" />
<group name="Vanilla_Land_misc_chickenCoop" pos="7569.32 213.768 5092.42" rpy="-0 0 -80" a="170" />
<group name="Vanilla_Land_misc_chickenCoop" pos="7580.03 140.257 12869.2" rpy="-0.00126808 0.0279472 -92.5979" a="-177.402" />
<group name="Vanilla_Land_misc_chickenCoop" pos="7580.15 140.208 12864.6" rpy="-0 0 -111.115" a="-158.885" />
<group name="Vanilla_Land_misc_chickenCoop" pos="7666.07 183.862 13246.7" rpy="0.0208178 0.0186889 -41.9156" a="131.916" />
<group name="Vanilla_Land_misc_chickenCoop" pos="7660.35 183.914 13244.6" rpy="-0 0 -7.41036" a="97.4104" />
<group name="Vanilla_Land_misc_chickenCoop" pos="7684.85 189.406 4910.38" rpy="-0 0 -150" a="-120" />
<group name="Vanilla_Land_misc_chickenCoop" pos="7711.29 128.371 12472.2" rpy="0.0463392 0.0313595 -34.0878" a="124.088" />
<group name="Vanilla_Land_misc_chickenCoop" pos="7768.94 119.044 12632.4" rpy="-0 0 -156.947" a="-113.053" />
<group name="Vanilla_Land_misc_chickenCoop" pos="7770.5 119.046 12629.6" rpy="-0.0130649 0.0466625 -105.642" a="-164.358" />
<group name="Vanilla_Land_misc_chickenCoop" pos="7949.56 151.106 13048.3" rpy="-0.0273803 0.00574268 -168.155" a="-101.845" />
<group name="Vanilla_Land_misc_chickenCoop" pos="8008.98 148.496 13043.9" rpy="-0 0 -33.1241" a="123.124" />
<group name="Vanilla_Land_misc_chickenCoop" pos="8016.88 148.667 13047.3" rpy="-0 0 -8.56521" a="98.5652" />
<group name="Vanilla_Land_misc_chickenCoop" pos="8013.64 148.644 13046.7" rpy="-0 0 -37.1249" a="127.125" />
<group name="Vanilla_Land_misc_chickenCoop" pos="8156.68 6.74436 3190.65" rpy="-0 0 -165.073" a="-104.927" />
<group name="Vanilla_Land_misc_chickenCoop" pos="8104.59 196.71 11526.2" rpy="-0 0 171.491" a="-81.4911" />
<group name="Vanilla_Land_misc_chickenCoop" pos="8213.47 180.197 11613.3" rpy="-0 0 -157.727" a="-112.273" />
<group name="Vanilla_Land_misc_chickenCoop" pos="8204.39 145.961 12176.7" rpy="-0.0736901 0.00697051 -174.596" a="-95.4037" />
<group name="Vanilla_Land_misc_chickenCoop" pos="8189.9 146.383 12180.8" rpy="-0.0386503 0.035292 -137.6" a="-132.4" />
<group name="Vanilla_Land_misc_chickenCoop" pos="8205.93 142.331 12251.3" rpy="0.0128092 0.0423398 -73.1677" a="163.168" />
<group name="Vanilla_Land_misc_chickenCoop" pos="8207.81 142.338 12246.2" rpy="-0.0109718 0.0257347 -113.091" a="-156.909" />
<group name="Vanilla_Land_misc_chickenCoop" pos="8259.12 146.36 12216.5" rpy="0.0341406 0.00290519 -4.86385" a="94.8638" />
<group name="Vanilla_Land_misc_chickenCoop" pos="8255.08 146.349 12215.4" rpy="0.0304705 0.0320668 -46.4622" a="136.462" />
<group name="Vanilla_Land_misc_chickenCoop" pos="8231.22 150.585 13123.9" rpy="-0 0 -20.5403" a="110.54" />
<group name="Vanilla_Land_misc_chickenCoop" pos="8339.67 134.924 13046.7" rpy="0.0103369 0.0259963 -68.3157" a="158.316" />
<group name="Vanilla_Land_misc_chickenCoop" pos="8395.65 140.868 4927.3" rpy="-0 0 0" a="90" />
<group name="Vanilla_Land_misc_chickenCoop" pos="8373.83 359.703 6629.22" rpy="-0 0 3.34755" a="86.6525" />
<group name="Vanilla_Land_misc_chickenCoop" pos="8386.11 132.388 12960.5" rpy="-0.0260848 -0.0101115 158.812" a="-68.8117" />
<group name="Vanilla_Land_misc_chickenCoop" pos="8390.3 132.42 12960.5" rpy="-0.0342509 -0.00094781 178.415" a="-88.4149" />
<group name="Vanilla_Land_misc_chickenCoop" pos="8341.42 134.733 13050" rpy="0.0169089 0.0102672 -31.2663" a="121.266" />
<group name="Vanilla_Land_misc_chickenCoop" pos="8459.86 360.314 6623.29" rpy="-0 0 93.3056" a="-3.3056" />
<group name="Vanilla_Land_misc_chickenCoop" pos="8405.16 360.199 6623.94" rpy="-0 0 93.8272" a="-3.8272" />
<group name="Vanilla_Land_misc_chickenCoop" pos="8451.74 357.149 6710.06" rpy="-0 0 -93.4184" a="-176.582" />
<group name="Vanilla_Land_misc_chickenCoop" pos="8437.93 107.057 12751.2" rpy="0.0188461 -0.00601255 17.6945" a="72.3055" />
<group name="Vanilla_Land_misc_chickenCoop" pos="8457.82 107.135 12760.7" rpy="-0 0 -118.641" a="-151.359" />
<group name="Vanilla_Land_misc_chickenCoop" pos="8408.54 107.208 12743.2" rpy="0.00674345 0.0185971 -70.069" a="160.069" />
<group name="Vanilla_Land_misc_chickenCoop" pos="8468.94 360.383 6627.17" rpy="-0 0 -177.107" a="-92.8933" />
<group name="Vanilla_Land_misc_chickenCoop" pos="8487.28 360.304 6631.8" rpy="-0 0 -91.0933" a="-178.907" />
<group name="Vanilla_Land_misc_chickenCoop" pos="8471.3 358.214 6696.86" rpy="-0 0 5.06999" a="84.93" />
<group name="Vanilla_Land_misc_chickenCoop" pos="8515.24 191.529 11942.4" rpy="-0 0 151.352" a="-61.3516" />
<group name="Vanilla_Land_misc_chickenCoop" pos="8517.52 104.874 12685.1" rpy="-0 0 64.403" a="25.597" />
<group name="Vanilla_Land_misc_chickenCoop" pos="8517.13 104.875 12682.1" rpy="-0.0154239 -0.0537851 106.001" a="-16.0012" />
<group name="Vanilla_Land_misc_chickenCoop" pos="8468.75 107.62 12817.7" rpy="0.0462839 -0.0143485 17.224" a="72.776" />
<group name="Vanilla_Land_misc_chickenCoop" pos="8460.19 107.865 12818.9" rpy="0.0197486 0.0198153 -45.0966" a="135.097" />
<group name="Vanilla_Land_misc_chickenCoop" pos="8560 189.455 12000.5" rpy="-0 0 -120.5" a="-149.5" />
<group name="Vanilla_Land_misc_chickenCoop" pos="8623.66 199.601 11895.8" rpy="-0 0 -119" a="-151" />
<group name="Vanilla_Land_misc_chickenCoop" pos="8658.68 6.90277 2469.34" rpy="-0 0 -0.937748" a="90.9377" />
<group name="Vanilla_Land_misc_chickenCoop" pos="8807.18 225.326 11575.7" rpy="-0 0 -180" a="-90" />
<group name="Vanilla_Land_misc_chickenCoop" pos="8781.11 220.89 11673.7" rpy="-0 0 -6.99998" a="97" />
<group name="Vanilla_Land_misc_chickenCoop" pos="8825.67 105.947 12914.9" rpy="-0 0 -166.097" a="-103.903" />
<group name="Vanilla_Land_misc_chickenCoop" pos="8830.04 105.46 12916.7" rpy="-0.029927 -0.0429388 124.875" a="-34.8752" />
<group name="Vanilla_Land_misc_chickenCoop" pos="9102.69 230.264 14423.2" rpy="-0 0 -179.46" a="-90.54" />
<group name="Vanilla_Land_misc_chickenCoop" pos="9127.25 256.676 4091.04" rpy="-0 0 -32" a="122" />
<group name="Vanilla_Land_misc_chickenCoop" pos="9155.7 234.465 14496.7" rpy="-0 0 93.0348" a="-3.0348" />
<group name="Vanilla_Land_misc_chickenCoop" pos="9131.07 241.377 14548.1" rpy="0.00045321 0.0395624 -89.3437" a="179.344" />
<group name="Vanilla_Land_misc_chickenCoop" pos="9220.88 80.4072 13624.6" rpy="0.0500369 0.0250408 -26.5855" a="116.586" />
<group name="Vanilla_Land_misc_chickenCoop" pos="9216.69 80.5606 13624.2" rpy="0.0277685 0.00340093 -6.98249" a="96.9825" />
<group name="Vanilla_Land_misc_chickenCoop" pos="9192.84 240.778 14577.7" rpy="-0 0 90.5193" a="-0.519272" />
<group name="Vanilla_Land_misc_chickenCoop" pos="9268.93 79.8235 13602.3" rpy="-0.0255537 -0.011387 155.982" a="-65.9817" />
<group name="Vanilla_Land_misc_chickenCoop" pos="9271.27 79.7464 13606.4" rpy="0.00257447 -0.0483885 86.9545" a="3.04551" />
<group name="Vanilla_Land_misc_chickenCoop" pos="9257.52 240.692 14602.7" rpy="-0.0018459 0.027915 -93.7832" a="-176.217" />
<group name="Vanilla_Land_misc_chickenCoop" pos="9327.19 78.1348 13599.5" rpy="-0 0 -175.664" a="-94.3363" />
<group name="Vanilla_Land_misc_chickenCoop" pos="9330.97 78.0838 13601.6" rpy="-0.0244154 -0.0240397 135.444" a="-45.4443" />
<group name="Vanilla_Land_misc_chickenCoop" pos="9316.21 78.1508 13596.7" rpy="-0 0 133.5" a="-43.4997" />
<group name="Vanilla_Land_misc_chickenCoop" pos="9338.39 78.4846 13632.3" rpy="-0 0 -169.263" a="-100.737" />
<group name="Vanilla_Land_misc_chickenCoop" pos="9323.15 80.9639 13669.3" rpy="-0 0 -81.9365" a="171.936" />
<group name="Vanilla_Land_misc_chickenCoop" pos="9358.9 232.913 14549.9" rpy="0.0395175 0.00193752 -2.80692" a="92.8069" />
<group name="Vanilla_Land_misc_chickenCoop" pos="9315.66 237.569 14590.5" rpy="0.0182862 -0.0448742 67.8292" a="22.1708" />
<group name="Vanilla_Land_misc_chickenCoop" pos="9405.54 81.6782 13685.7" rpy="-0 0 -105.535" a="-164.465" />
<group name="Vanilla_Land_misc_chickenCoop" pos="9380.91 84.6829 13747.5" rpy="-0 0 20.7498" a="69.2502" />
<group name="Vanilla_Land_misc_chickenCoop" pos="9376.46 84.3442 13746.1" rpy="-0 0 -16.2997" a="106.3" />
<group name="Vanilla_Land_misc_chickenCoop" pos="9394.31 236.796 14616.4" rpy="-0 0 113.134" a="-23.1337" />
<group name="Vanilla_Land_misc_chickenCoop" pos="9395.9 237.769 14645.8" rpy="-0.00401086 0.027687 -98.2428" a="-171.757" />
<group name="Vanilla_Land_misc_chickenCoop" pos="9447.18 297.329 8666.13" rpy="0.0316048 -0.0132347 22.7218" a="67.2782" />
<group name="Vanilla_Land_misc_chickenCoop" pos="9476.96 302.496 8724.76" rpy="0.0332853 -0.00813067 13.7269" a="76.2731" />
<group name="Vanilla_Land_misc_chickenCoop" pos="9459.18 300.661 8704.77" rpy="-0.0181932 -0.0564896 107.852" a="-17.8518" />
<group name="Vanilla_Land_misc_chickenCoop" pos="9435.68 304.718 8769.07" rpy="-0 0 0" a="90" />
<group name="Vanilla_Land_misc_chickenCoop" pos="9474.21 304.362 8876.29" rpy="-0 0 0" a="90" />
<group name="Vanilla_Land_misc_chickenCoop" pos="9475.88 304.324 8888.72" rpy="-0.0258697 0.0106495 -157.625" a="-112.375" />
<group name="Vanilla_Land_misc_chickenCoop" pos="9438.8 82.4377 13723.3" rpy="-0 0 -105.524" a="-164.476" />
<group name="Vanilla_Land_misc_chickenCoop" pos="9436.69 81.3553 13690.5" rpy="0.0123522 -0.0251014 63.7986" a="26.2014" />
<group name="Vanilla_Land_misc_chickenCoop" pos="9435.37 232.569 14559.8" rpy="-0 0 20.3205" a="69.6795" />
<group name="Vanilla_Land_misc_chickenCoop" pos="9454.05 237.42 14610.7" rpy="0.0368531 0.0314632 -40.4889" a="130.489" />
<group name="Vanilla_Land_misc_chickenCoop" pos="9425.32 245.95 14708.2" rpy="-5.42959e-05 -0.0197819 90.1573" a="-0.157257" />
<group name="Vanilla_Land_misc_chickenCoop" pos="9420.07 250.228 14735.6" rpy="-0 0 65.6901" a="24.3099" />
<group name="Vanilla_Land_misc_chickenCoop" pos="9467.87 246.112 14723.8" rpy="0.0385165 -0.00904795 13.2197" a="76.7803" />
<group name="Vanilla_Land_misc_chickenCoop" pos="9523.87 7.32329 1830.34" rpy="0.00921411 0.0264151 -70.7702" a="160.77" />
<group name="Vanilla_Land_misc_chickenCoop" pos="9496.62 303.673 8750.66" rpy="-0.00596064 -0.0273336 102.302" a="-12.3019" />
<group name="Vanilla_Land_misc_chickenCoop" pos="9517.79 304.235 8867.41" rpy="-0 0 91.8841" a="-1.88406" />
<group name="Vanilla_Land_misc_chickenCoop" pos="9492.08 304.628 8909.08" rpy="0.0176629 -0.00890786 26.763" a="63.237" />
<group name="Vanilla_Land_misc_chickenCoop" pos="9489.89 237.938 14615.5" rpy="-0 0 150.871" a="-60.8714" />
<group name="Vanilla_Land_misc_chickenCoop" pos="9591.98 202.565 6622.31" rpy="-0 0 -97.7378" a="-172.262" />
<group name="Vanilla_Land_misc_chickenCoop" pos="9591.16 304.584 8876.08" rpy="-0.00528791 -0.0190621 105.504" a="-15.5042" />
<group name="Vanilla_Land_misc_chickenCoop" pos="9572.03 304.271 8844.15" rpy="-0.0108418 -0.0165464 123.234" a="-33.2343" />
<group name="Vanilla_Land_misc_chickenCoop" pos="9579.23 255.554 14722.7" rpy="-0 0 -134.672" a="-135.328" />
<group name="Vanilla_Land_misc_chickenCoop" pos="9645.18 209.089 6554.36" rpy="-0 0 102.265" a="-12.2655" />
<group name="Vanilla_Land_misc_chickenCoop" pos="9626.67 83.2942 13798.5" rpy="-0.0185902 0.020906 -131.644" a="-138.356" />
<group name="Vanilla_Land_misc_chickenCoop" pos="9626.04 83.2951 13802.6" rpy="-3.90949e-05 0.048457 -90.0462" a="-179.954" />
<group name="Vanilla_Land_misc_chickenCoop" pos="9699.84 198.046 6779.95" rpy="-0 0 -152.096" a="-117.904" />
<group name="Vanilla_Land_misc_chickenCoop" pos="9709.69 198.42 6821.96" rpy="-0 0 -5.78046" a="95.7805" />
<group name="Vanilla_Land_misc_chickenCoop" pos="9752.55 4.29285 1783.5" rpy="-0 0 -145.814" a="-124.186" />
<group name="Vanilla_Land_misc_chickenCoop" pos="9889.22 255.016 5384.73" rpy="-0 0 100" a="-9.99998" />
<group name="Vanilla_Land_misc_chickenCoop" pos="9955.56 6.76436 1982.38" rpy="-0 0 69.5357" a="20.4643" />
<group name="Vanilla_Land_misc_chickenCoop" pos="9949.74 12.2199 2156.58" rpy="-0 0 -82.7123" a="172.712" />
<group name="Vanilla_Land_misc_chickenCoop" pos="9997.34 13.3623 2152.54" rpy="0.0671636 0.0136067 -11.4526" a="101.453" />
<group name="Vanilla_Land_misc_chickenCoop" pos="10045.3 13.1006 2164" rpy="-0.0193214 0.0345264 -119.232" a="-150.768" />
<group name="Vanilla_Land_misc_chickenCoop" pos="10060.6 16.1546 2209.42" rpy="-0 0 61.3238" a="28.6762" />
<group name="Vanilla_Land_misc_chickenCoop" pos="10051.8 259.218 5688.97" rpy="-0 0 43.7607" a="46.2393" />
<group name="Vanilla_Land_misc_chickenCoop" pos="10120.2 6.9566 2141.01" rpy="-0 0 -17.8389" a="107.839" />
<group name="Vanilla_Land_misc_chickenCoop" pos="10089.3 15.834 2218.33" rpy="-0.0181471 0.0529285 -108.925" a="-161.075" />
<group name="Vanilla_Land_misc_chickenCoop" pos="10110.8 12.5848 2174.53" rpy="-0 0 -17.008" a="107.008" />
<group name="Vanilla_Land_misc_chickenCoop" pos="10111.6 23.1912 2286.21" rpy="-0.0359027 0.0166249 -155.153" a="-114.847" />
<group name="Vanilla_Land_misc_chickenCoop" pos="10199.4 24.0351 2329.04" rpy="0.00686714 0.0271201 -75.7907" a="165.791" />
<group name="Vanilla_Land_misc_chickenCoop" pos="10208.1 6.46938 2136.06" rpy="-0.0278645 -0.00249525 174.883" a="-84.8828" />
<group name="Vanilla_Land_misc_chickenCoop" pos="10252.1 16.0317 2252.46" rpy="0.0176322 -0.0217201 50.9306" a="39.0694" />
<group name="Vanilla_Land_misc_chickenCoop" pos="10254.7 245.411 5578.9" rpy="-0 0 -25.9156" a="115.916" />
<group name="Vanilla_Land_misc_chickenCoop" pos="10232 143.743 9805.95" rpy="-0 0 87.1115" a="2.88846" />
<group name="Vanilla_Land_misc_chickenCoop" pos="10212 147.143 9859.93" rpy="-0 0 -87.8106" a="177.811" />
<group name="Vanilla_Land_misc_chickenCoop" pos="10318.1 133.368 9841.16" rpy="-0 0 5.75061" a="84.2494" />
<group name="Vanilla_Land_misc_chickenCoop" pos="10334.2 16.7819 2875.92" rpy="-0.0151545 -0.0235159 122.799" a="-32.7992" />
<group name="Vanilla_Land_misc_chickenCoop" pos="10337.4 130.711 9837.51" rpy="-0 0 -177.573" a="-92.4271" />
<group name="Vanilla_Land_misc_chickenCoop" pos="10526.5 130.197 9709.98" rpy="-0 0 141.293" a="-51.2934" />
<group name="Vanilla_Land_misc_chickenCoop" pos="10556.1 106.609 10196.6" rpy="-0 0 4.99999" a="85" />
<group name="Vanilla_Land_misc_chickenCoop" pos="10593.3 6.50086 2111.86" rpy="-0.040799 -0.0169894 67.3923" a="22.6077" />
<group name="Vanilla_Land_misc_chickenCoop" pos="10606.1 99.241 9973.26" rpy="-0 0 -51.48" a="141.48" />
<group name="Vanilla_Land_misc_chickenCoop" pos="10629.3 6.35043 2304.02" rpy="-0 0 54.8864" a="35.1136" />
<group name="Vanilla_Land_misc_chickenCoop" pos="10633.6 212.405 8102.4" rpy="0.0135706 -0.0244642 60.9824" a="29.0176" />
<group name="Vanilla_Land_misc_chickenCoop" pos="10716.4 56.0286 14363.6" rpy="0.00746426 -0.0269619 74.5255" a="15.4745" />
<group name="Vanilla_Land_misc_chickenCoop" pos="10717.1 55.6993 14361.3" rpy="0.023566 -0.024873 46.5456" a="43.4544" />
<group name="Vanilla_Land_misc_chickenCoop" pos="10825 6.45724 2507.32" rpy="-0 0 -74.69" a="164.69" />
<group name="Vanilla_Land_misc_chickenCoop" pos="10849.7 240.835 12405.5" rpy="-0.0226023 0.0164861 -143.893" a="-126.107" />
<group name="Vanilla_Land_misc_chickenCoop" pos="10856.4 239.484 12403.4" rpy="-0.0279157 -0.00183507 176.239" a="-86.239" />
<group name="Vanilla_Land_misc_chickenCoop" pos="10828.7 246.403 12414.3" rpy="-0 0 151.528" a="-61.5281" />
<group name="Vanilla_Land_misc_chickenCoop" pos="10859.6 52.0989 14388.8" rpy="-0.0269179 0.00762106 -164.192" a="-105.808" />
<group name="Vanilla_Land_misc_chickenCoop" pos="10860.3 52.1775 14392" rpy="-0 0 -109.702" a="-160.298" />
<group name="Vanilla_Land_misc_chickenCoop" pos="11142.9 76.9168 6585.23" rpy="-0 0 -151.136" a="-118.864" />
<group name="Vanilla_Land_misc_chickenCoop" pos="11210.2 76.9799 6574.47" rpy="-0 0 -179.727" a="-90.2727" />
<group name="Vanilla_Land_misc_chickenCoop" pos="11195 200.887 12130.5" rpy="-0 0 -163.597" a="-106.403" />
<group name="Vanilla_Land_misc_chickenCoop" pos="11191.6 201.129 12134.3" rpy="-0 0 -118.614" a="-151.386" />
<group name="Vanilla_Land_misc_chickenCoop" pos="11190.6 202.868 12385.2" rpy="-0 0 58.6606" a="31.3394" />
<group name="Vanilla_Land_misc_chickenCoop" pos="11195.6 202.34 12383" rpy="-0 0 8.00955" a="81.9904" />
<group name="Vanilla_Land_misc_chickenCoop" pos="11303.8 255.071 5500.68" rpy="0.0260768 0.010132 -21.2334" a="111.233" />
<group name="Vanilla_Land_misc_chickenCoop" pos="11318.1 74.7215 6599.18" rpy="-0 0 82.6483" a="7.35169" />
<group name="Vanilla_Land_misc_chickenCoop" pos="11326.2 191.09 12238.7" rpy="-0 0 110.085" a="-20.0855" />
<group name="Vanilla_Land_misc_chickenCoop" pos="11292.7 195.004 12296.6" rpy="0.0229115 -0.0160537 35.0183" a="54.9817" />
<group name="Vanilla_Land_misc_chickenCoop" pos="11289.3 195.117 12297.8" rpy="-0 0 0" a="90" />
<group name="Vanilla_Land_misc_chickenCoop" pos="11357.1 254.05 5485.14" rpy="-0 0 -90.2395" a="-179.761" />
<group name="Vanilla_Land_misc_chickenCoop" pos="11358.6 254.347 5506.26" rpy="-0 0 58.449" a="31.551" />
<group name="Vanilla_Land_misc_chickenCoop" pos="11357 77.5633 6627.57" rpy="-0 0 -10.1831" a="100.183" />
<group name="Vanilla_Land_misc_chickenCoop" pos="11394.8 59.5356 14940.6" rpy="-0.034264 -4.7321e-05 179.921" a="-89.9209" />
<group name="Vanilla_Land_misc_chickenCoop" pos="11565.6 70.8793 6647.12" rpy="-0 0 89.5303" a="0.469666" />
<group name="Vanilla_Land_misc_chickenCoop" pos="11547.4 151.435 12378.5" rpy="-0 0 -170.548" a="-99.4518" />
<group name="Vanilla_Land_misc_chickenCoop" pos="11580.7 151.399 12371.8" rpy="-0 0 -169.321" a="-100.679" />
<group name="Vanilla_Land_misc_chickenCoop" pos="11628.3 150.268 12404.5" rpy="0.0168286 -0.0103983 31.7118" a="58.2882" />
<group name="Vanilla_Land_misc_chickenCoop" pos="11607 147.497 12471" rpy="-0 0 107.273" a="-17.2733" />
<group name="Vanilla_Land_misc_chickenCoop" pos="11663.8 63.2818 14792.4" rpy="-0.0189986 0.00551197 -163.821" a="-106.179" />
<group name="Vanilla_Land_misc_chickenCoop" pos="11812.1 61.2833 9047.95" rpy="-0 0 -45" a="135" />
<group name="Vanilla_Land_misc_chickenCoop" pos="11772.6 65.7261 9090.69" rpy="-0 0 -101.544" a="-168.456" />
<group name="Vanilla_Land_misc_chickenCoop" pos="11859.5 54.5859 9159.18" rpy="-0 0 -173.318" a="-96.6817" />
<group name="Vanilla_Land_misc_chickenCoop" pos="11859.3 87.7258 13903.9" rpy="0.0147107 0.0132258 -41.9576" a="131.958" />
<group name="Vanilla_Land_misc_chickenCoop" pos="11931.1 54.4484 9208.26" rpy="-0 0 -175.184" a="-94.8157" />
<group name="Vanilla_Land_misc_chickenCoop" pos="11885.5 88.8337 13901.9" rpy="-0 0 52.7024" a="37.2976" />
<group name="Vanilla_Land_misc_chickenCoop" pos="11904.2 90.5169 13895.2" rpy="-0 0 -30.5957" a="120.596" />
<group name="Vanilla_Land_misc_chickenCoop" pos="11980.8 56.1785 8960.29" rpy="-0 0 -175.884" a="-94.116" />
<group name="Vanilla_Land_misc_chickenCoop" pos="12029.3 94.7786 13742.9" rpy="-0 0 -142.89" a="-127.11" />
<group name="Vanilla_Land_misc_chickenCoop" pos="12027.5 94.8628 13745.9" rpy="-0.0024308 0.0278702 -94.9846" a="-175.015" />
<group name="Vanilla_Land_misc_chickenCoop" pos="12087.8 6.73672 3523.41" rpy="0.038859 0.00736316 -100.729" a="-169.271" />
<group name="Vanilla_Land_misc_chickenCoop" pos="12078.9 5.29923 3656.64" rpy="-0 0 -13.0094" a="103.009" />
<group name="Vanilla_Land_misc_chickenCoop" pos="12090.2 6.20072 3600.45" rpy="-0 0 -11.551" a="101.551" />
<group name="Vanilla_Land_misc_chickenCoop" pos="12072.1 5.366 3683.05" rpy="0.00968432 -0.0383465 -14.1736" a="104.174" />
<group name="Vanilla_Land_misc_chickenCoop" pos="12060.8 6.54135 3709.34" rpy="-0 0 161.016" a="-71.0159" />
<group name="Vanilla_Land_misc_chickenCoop" pos="12112.1 51.9267 9017.86" rpy="-0 0 -153.538" a="-116.462" />
<group name="Vanilla_Land_misc_chickenCoop" pos="12069.9 38.798 9343.49" rpy="-0.0392681 0.0283919 -144.132" a="-125.868" />
<group name="Vanilla_Land_misc_chickenCoop" pos="12082.9 97.9675 13661.6" rpy="0.0101719 -0.0260612 68.6788" a="21.3212" />
<group name="Vanilla_Land_misc_chickenCoop" pos="12080.6 97.8783 13664.7" rpy="0.0191785 -0.00484895 14.1889" a="75.8111" />
<group name="Vanilla_Land_misc_chickenCoop" pos="12172.7 5.63399 3465.93" rpy="-0 0 179.281" a="-89.281" />
<group name="Vanilla_Land_misc_chickenCoop" pos="12162 6.39217 3550.12" rpy="-0 0 -175.712" a="-94.2877" />
<group name="Vanilla_Land_misc_chickenCoop" pos="12122.8 191.089 7238.14" rpy="-0 0 96.2724" a="-6.27238" />
<group name="Vanilla_Land_misc_chickenCoop" pos="12136.7 25.7242 9483.93" rpy="-0 0 -41.0246" a="131.025" />
<group name="Vanilla_Land_misc_chickenCoop" pos="12132.9 103.995 13462.7" rpy="0.0595812 0.0392107 -33.3491" a="123.349" />
<group name="Vanilla_Land_misc_chickenCoop" pos="12135.5 103.905 13465.1" rpy="0.0194996 0.0200605 -45.8124" a="135.812" />
<group name="Vanilla_Land_misc_chickenCoop" pos="12182.5 183.862 7317.48" rpy="-0 0 103.203" a="-13.2028" />
<group name="Vanilla_Land_misc_chickenCoop" pos="12294.3 166.778 7332.57" rpy="-0 0 -146.125" a="-123.875" />
<group name="Vanilla_Land_misc_chickenCoop" pos="12295.8 16.9331 9511" rpy="0.0277852 -0.0281464 -44.63" a="134.63" />
<group name="Vanilla_Land_misc_chickenCoop" pos="12262.3 93.5475 10618.7" rpy="-0 0 179.385" a="-89.3851" />
<group name="Vanilla_Land_misc_chickenCoop" pos="12273.1 104.795 10850.6" rpy="-0 0 -174.422" a="-95.5778" />
<group name="Vanilla_Land_misc_chickenCoop" pos="12269.1 105.085 10853.7" rpy="-0 0 112.599" a="-22.5985" />
<group name="Vanilla_Land_misc_chickenCoop" pos="12244 106.358 10892.5" rpy="-0.00920619 0.0264178 -109.213" a="-160.787" />
<group name="Vanilla_Land_misc_chickenCoop" pos="12250.7 93.171 13837.3" rpy="-0.0181015 0.0213305 -130.319" a="-139.681" />
<group name="Vanilla_Land_misc_chickenCoop" pos="12254.1 92.9393 13836.2" rpy="-0.0192661 0.00448821 -166.886" a="-103.114" />
<group name="Vanilla_Land_misc_chickenCoop" pos="12302.5 49.2078 8465.53" rpy="-0 0 -9.99999" a="100" />
<group name="Vanilla_Land_misc_chickenCoop" pos="12320.9 34.7321 9154.61" rpy="-0 0 60" a="30" />
<group name="Vanilla_Land_misc_chickenCoop" pos="12329.7 34.7534 9138.65" rpy="-0 0 60" a="30" />
<group name="Vanilla_Land_misc_chickenCoop" pos="12324.2 34.7437 9148.53" rpy="-0 0 60" a="30" />
<group name="Vanilla_Land_misc_chickenCoop" pos="12317.1 109.531 11013.5" rpy="0.00223384 0.0278867 -85.4201" a="175.42" />
<group name="Vanilla_Land_misc_chickenCoop" pos="12325 86.6739 13868.9" rpy="0.0135504 -0.0371723 69.9717" a="20.0283" />
<group name="Vanilla_Land_misc_chickenCoop" pos="12323.5 86.7636 13870.9" rpy="0.0211194 -0.0183474 40.9822" a="49.0178" />
<group name="Vanilla_Land_misc_chickenCoop" pos="12411.7 8.64714 9519.15" rpy="0.00401497 0.0393461 -174.174" a="-95.8264" />
<group name="Vanilla_Land_misc_chickenCoop" pos="12363.4 11.3344 9521.85" rpy="0.000913741 0.0395399 -178.676" a="-91.3239" />
<group name="Vanilla_Land_misc_chickenCoop" pos="12391.1 9.29253 9572.24" rpy="0.0390962 -0.00597669 -81.3084" a="171.308" />
<group name="Vanilla_Land_misc_chickenCoop" pos="12380 10.6191 9599.94" rpy="-0 0 93.2524" a="-3.25239" />
<group name="Vanilla_Land_misc_chickenCoop" pos="12361.5 12.0647 9721.36" rpy="-0.0458407 0.0156692 144.145" a="-54.1451" />
<group name="Vanilla_Land_misc_chickenCoop" pos="12381.7 106.431 10975.5" rpy="-0 0 5.4774" a="84.5226" />
<group name="Vanilla_Land_misc_chickenCoop" pos="12374.8 107.719 11014.1" rpy="-0 0 10.1523" a="79.8477" />
<group name="Vanilla_Land_misc_chickenCoop" pos="12402.6 115.49 14770.1" rpy="-0 0 -103.967" a="-166.033" />
<group name="Vanilla_Land_misc_chickenCoop" pos="12400.9 116.56 14777.6" rpy="-0 0 -93.9903" a="-176.01" />
<group name="Vanilla_Land_misc_chickenCoop" pos="12401.6 115.95 14773.8" rpy="-0 0 -94.1913" a="-175.809" />
<group name="Vanilla_Land_misc_chickenCoop" pos="12537.5 107.481 14780.7" rpy="-0 0 -149.671" a="-120.329" />
<group name="Vanilla_Land_misc_chickenCoop" pos="12527.4 106.306 14764.9" rpy="-0 0 12.8264" a="77.1736" />
<group name="Vanilla_Land_misc_chickenCoop" pos="12540.4 107.414 14781.6" rpy="-0 0 150.712" a="-60.7122" />
<group name="Vanilla_Land_misc_chickenCoop" pos="12649.4 47.3966 5644.07" rpy="-0 0 63.1944" a="26.8056" />
<group name="Vanilla_Land_misc_chickenCoop" pos="12662.8 180.831 4354.92" rpy="-0 0 -3.00003" a="93" />
<group name="Vanilla_Land_misc_chickenCoop" pos="12667.2 6.65647 9479.84" rpy="-0 0 -80" a="170" />
<group name="Vanilla_Land_misc_chickenCoop" pos="12749 28.9679 8094.84" rpy="-0 0 38.1484" a="51.8516" />
<group name="Vanilla_Land_misc_chickenCoop" pos="12756.2 95.1033 14669.9" rpy="-0 0 -134.425" a="-135.575" />
<group name="Vanilla_Land_misc_chickenCoop" pos="12754.5 95.2503 14672" rpy="-0.0103395 0.0168648 -121.512" a="-148.488" />
<group name="Vanilla_Land_misc_chickenCoop" pos="12826.6 171.979 4432.18" rpy="-0 0 86" a="4.00001" />
<group name="Vanilla_Land_misc_chickenCoop" pos="12834 6.51001 10043.6" rpy="-0 0 99.6735" a="-9.6735" />
<group name="Vanilla_Land_misc_chickenCoop" pos="12827.4 6.49289 10090.1" rpy="-0 0 12.3185" a="77.6815" />
<group name="Vanilla_Land_misc_chickenCoop" pos="12830.6 6.65205 10170.6" rpy="-0 0 27.4246" a="62.5754" />
<group name="Vanilla_Land_misc_chickenCoop" pos="12825.2 58.531 15046.1" rpy="0.00667905 -0.0186204 70.2673" a="19.7327" />
<group name="Vanilla_Land_misc_chickenCoop" pos="12868.4 172.544 4449.7" rpy="-0.0268153 -0.00797472 163.438" a="-73.4378" />
<group name="Vanilla_Land_misc_chickenCoop" pos="12861.8 20.996 8029.82" rpy="-0 0 -66.5204" a="156.52" />
<group name="Vanilla_Land_misc_chickenCoop" pos="12841.7 22.7035 8160.99" rpy="-0 0 -13.4035" a="103.403" />
<group name="Vanilla_Land_misc_chickenCoop" pos="12860.1 6.51589 10049.3" rpy="-0 0 10.3354" a="79.6646" />
<group name="Vanilla_Land_misc_chickenCoop" pos="12898.8 6.54591 10168.3" rpy="-0.0168241 0.0223518 -126.969" a="-143.031" />
<group name="Vanilla_Land_misc_chickenCoop" pos="12861.3 6.70901 10203.3" rpy="0.00878767 0.02656 -71.6926" a="161.693" />
<group name="Vanilla_Land_misc_chickenCoop" pos="12883.9 95.5054 14612.8" rpy="-0.0376811 0.0120633 -162.248" a="-107.752" />
<group name="Vanilla_Land_misc_chickenCoop" pos="12915.1 26.7607 6791.96" rpy="-0 0 -14.3941" a="104.394" />
<group name="Vanilla_Land_misc_chickenCoop" pos="12947.3 26.5955 7981.85" rpy="-0 0 -51.3083" a="141.308" />
<group name="Vanilla_Land_misc_chickenCoop" pos="12901.7 10.4359 8312.1" rpy="-0 0 72.5794" a="17.4206" />
<group name="Vanilla_Land_misc_chickenCoop" pos="12910.4 6.75472 10039.8" rpy="-0.00628822 -0.0187559 108.535" a="-18.5345" />
<group name="Vanilla_Land_misc_chickenCoop" pos="12951.4 6.73438 10223.1" rpy="0.0113376 0.0162107 -55.0314" a="145.031" />
<group name="Vanilla_Land_misc_chickenCoop" pos="12900 97.495 14618.5" rpy="0.00496277 -0.0557325 84.9114" a="5.08856" />
<group name="Vanilla_Land_misc_chickenCoop" pos="12974.7 25.5764 6764.37" rpy="-0 0 73.2344" a="16.7656" />
<group name="Vanilla_Land_misc_chickenCoop" pos="13000.4 6.34705 8193.77" rpy="-0 0 175.325" a="-85.325" />
<group name="Vanilla_Land_misc_chickenCoop" pos="12979 95.9069 14557.4" rpy="-0.0257132 0.0110222 -156.797" a="-113.203" />
<group name="Vanilla_Land_misc_chickenCoop" pos="12975.4 99.6609 14591.5" rpy="-0 0 -133.974" a="-136.026" />
<group name="Vanilla_Land_misc_chickenCoop" pos="12977.9 99.6773 14588.7" rpy="-0.0171884 0.00979208 -150.33" a="-119.67" />
<group name="Vanilla_Land_misc_chickenCoop" pos="13288.8 4.77511 6279.84" rpy="-0 0 0.541041" a="89.459" />
<group name="Vanilla_Land_misc_chickenCoop" pos="13338.8 6.51194 6319.88" rpy="0.000503405 -0.0395472 -0.72929" a="90.7293" />
<group name="Vanilla_Land_misc_chickenCoop" pos="13379.5 95.0735 12815.2" rpy="-0 0 152.756" a="-62.7561" />
<group name="Vanilla_Land_misc_chickenCoop" pos="13369.2 95.818 12905.8" rpy="-0 0 137.258" a="-47.2577" />
<group name="Vanilla_Land_misc_chickenCoop" pos="13373.2 95.6012 12906.7" rpy="-0 0 170.545" a="-80.5453" />
<group name="Vanilla_Land_misc_chickenCoop" pos="13430.9 4.20127 2823.39" rpy="-0 0 27.3312" a="62.6688" />
<group name="Vanilla_Land_misc_chickenCoop" pos="13424.7 4.09564 2823.34" rpy="-0 0 -27.2085" a="117.209" />
<group name="Vanilla_Land_misc_chickenCoop" pos="13380.3 6.55487 5974.98" rpy="0.0197616 0.000581789 -91.6863" a="-178.314" />
<group name="Vanilla_Land_misc_chickenCoop" pos="13432.7 6.33101 6259.97" rpy="-0 0 -113.494" a="-156.506" />
<group name="Vanilla_Land_misc_chickenCoop" pos="13381.6 6.46428 6388.16" rpy="-0 0 -5.28229" a="95.2823" />
<group name="Vanilla_Land_misc_chickenCoop" pos="13382.4 94.9662 12816.1" rpy="-0.0184609 -0.00710785 158.942" a="-68.9422" />
<group name="Vanilla_Land_misc_chickenCoop" pos="13607.1 13.3131 13956.4" rpy="-0 0 103.147" a="-13.1471" />
<group name="Vanilla_Land_misc_chickenCoop" pos="13733.4 22.2131 13311" rpy="-0 0 24.8984" a="65.1016" />
<group name="Vanilla_Land_misc_chickenCoop" pos="13712.8 22.6086 13313.8" rpy="-0 0 7.96937" a="82.0306" />
<group name="Vanilla_Land_misc_chickenCoop" pos="13716.1 22.5184 13286.1" rpy="-0 0 117.82" a="-27.8196" />
<group name="Vanilla_Land_misc_chickenCoop" pos="13715.4 22.5944 13312.7" rpy="-0 0 40.2366" a="49.7634" />
<group name="Vanilla_Land_misc_chickenCoop" pos="13715 22.5429 13282.5" rpy="-0 0 60.033" a="29.967" />
<group name="Vanilla_Land_misc_chickenCoop" pos="13768.5 21.2303 13252.9" rpy="0.00958597 0.0431838 -77.4844" a="167.484" />
<group name="Vanilla_Land_misc_chickenCoop" pos="13768.8 21.2681 13248.4" rpy="-0.0197455 0.0395835 -116.511" a="-153.489" />
<group name="Vanilla_Land_misc_chickenCoop" pos="13771.6 20.8143 13302.3" rpy="0.0194737 0.00347891 -10.1289" a="100.129" />
<group name="Vanilla_Land_misc_chickenCoop" pos="13768.1 20.824 13300.7" rpy="0.0224346 0.047287 -64.6187" a="154.619" />
<group name="Vanilla_Land_misc_chickenCoop" pos="14035.6 140.46 15079.2" rpy="-0.0137037 -0.0142666 133.847" a="-43.8469" />
<group name="Vanilla_Land_misc_chickenCoop" pos="13986.2 139.75 15061.2" rpy="-0 0 -125.945" a="-144.055" />
<group name="Vanilla_Land_misc_chickenCoop" pos="14042.6 140.553 15081.6" rpy="0.014214 -0.0137582 44.0665" a="45.9335" />
<group name="Vanilla_Land_misc_chickenCoop" pos="14118.3 135.783 14955.2" rpy="-0.0365728 0.0317885 -139.003" a="-130.997" />
<group name="Vanilla_Land_misc_chickenCoop" pos="14233.5 128.775 14901.9" rpy="-0 0 39.9662" a="50.0338" />
<group name="Vanilla_Land_misc_chickenCoop" pos="14354.5 127.226 14813.8" rpy="-0 0 86.8829" a="3.11705" />
</map>
